rd_mkdocs_puml/__init__.py
rd_mkdocs_puml/encoder.py
rd_mkdocs_puml/plugin.py
rd_mkdocs_puml/puml.py
rd_mkdocs_puml-1.2.4.dist-info/entry_points.txt
rd_mkdocs_puml-1.2.4.dist-info/LICENSE
rd_mkdocs_puml-1.2.4.dist-info/WHEEL
rd_mkdocs_puml-1.2.4.dist-info/METADATA
rd_mkdocs_puml-1.2.4.dist-info/RECORD
