Metadata-Version: 2.1
Name: rd_mkdocs_puml
Version: 1.2.4
Summary: Package that brings PlantUML to MkDocs
Author-email: Rishabh Devgon <devgon.rishabh@gmail.com>
Requires-Python: >=3.8
Classifier: License :: OSI Approved :: MIT License
Requires-Dist: requests >= 2.27, < 3.0
Requires-Dist: markdown >= 3.2.1, < 4.0
Requires-Dist: mkdocs >= 1.3, < 2.0
Project-URL: Home, https://github.com/RishabhDev42/rd_mkdocs_puml
